setup.py
simpleCalci/__init__.py
simpleCalci/calculator.py
simpleCalci.egg-info/PKG-INFO
simpleCalci.egg-info/SOURCES.txt
simpleCalci.egg-info/dependency_links.txt
simpleCalci.egg-info/not-zip-safe
simpleCalci.egg-info/top_level.txt