Metadata-Version: 1.0
Name: simpleCalci
Version: 0.4
Summary: Calculator to perform simple math operations
Home-page: UNKNOWN
Author: UNKNOWN
Author-email: UNKNOWN
License: UNKNOWN
Platform: UNKNOWN
